z80dis/__init__.py
z80dis/z80.py
z80dis-1.0.6.dist-info/LICENSE
z80dis-1.0.6.dist-info/METADATA
z80dis-1.0.6.dist-info/WHEEL
z80dis-1.0.6.dist-info/top_level.txt
z80dis-1.0.6.dist-info/RECORD
