Metadata-Version: 2.1
Name: z80dis
Version: 1.0.6
Summary: Z80 disassembler library
Home-page: https://github.com/lwerdna/z80dis
Author: Andrew Lamoureux
Author-email: foo@bar.com
License: UNKNOWN
Platform: UNKNOWN
Classifier: Programming Language :: Python :: 3
Classifier: License :: Public Domain
Classifier: Operating System :: OS Independent
